the_hangman_wordlist/__init__.py
the_hangman_wordlist/hangman_wordlist.py
the_hangman_wordlist-1.0.5.dist-info/METADATA
the_hangman_wordlist-1.0.5.dist-info/WHEEL
the_hangman_wordlist-1.0.5.dist-info/licenses/LICENSE
the_hangman_wordlist-1.0.5.dist-info/RECORD
