Metadata-Version: 2.3
Name: the_hangman_wordlist
Version: 1.0.5
Summary: A simple (and small) library to randomly pick hangman words from a predefined wordlist.
Project-URL: Homepage, https://thebiemgamer.github.io/TheHangmanWordlist
Project-URL: Source Code, https://github.com/TheBiemGamer/TheHangmanWordlist
Author: Noah Bozkurt, Jurriaan Portier
License-File: LICENSE
Classifier: License :: OSI Approved :: MIT License
Classifier: Operating System :: OS Independent
Classifier: Programming Language :: Python :: 3
Requires-Python: >=3.8
Requires-Dist: importlib-metadata
Requires-Dist: requests
